mcp_traffic/__init__.py
mcp_traffic/cli.py
mcp_traffic/collectors/__init__.py
mcp_traffic/collectors/traffic_collector.py
mcp_traffic/utils/__init__.py
mcp_traffic/utils/api_client.py
mcp_traffic/utils/config.py
mcp_traffic/utils/logger.py
mcp_traffic-1.0.0.dist-info/licenses/LICENSE
mcp_traffic-1.0.0.dist-info/METADATA
mcp_traffic-1.0.0.dist-info/WHEEL
mcp_traffic-1.0.0.dist-info/entry_points.txt
mcp_traffic-1.0.0.dist-info/top_level.txt
mcp_traffic-1.0.0.dist-info/RECORD
