Metadata-Version: 2.4
Name: mcp-traffic
Version: 1.0.0
Summary: Tokyo traffic data collection and analysis system using ODPT API
Author-email: Tatsuru Kikuchi <contact@mcp-traffic.example.com>
Maintainer-email: Tatsuru Kikuchi <contact@mcp-traffic.example.com>
License: MIT License
Project-URL: Homepage, https://tatsuru-kikuchi.github.io/MCP-traffic
Project-URL: Documentation, https://tatsuru-kikuchi.github.io/MCP-traffic/docs/
Project-URL: Dashboard, https://tatsuru-kikuchi.github.io/MCP-traffic/dashboard.html
Project-URL: Repository, https://github.com/Tatsuru-Kikuchi/MCP-traffic
Project-URL: Bug Tracker, https://github.com/Tatsuru-Kikuchi/MCP-traffic/issues
Project-URL: Changelog, https://github.com/Tatsuru-Kikuchi/MCP-traffic/blob/main/CHANGELOG.md
Keywords: tokyo,traffic,transportation,odpt,data-collection,japan,transit,api,real-time,monitoring
Classifier: Development Status :: 5 - Production/Stable
Classifier: Intended Audience :: Developers
Classifier: Intended Audience :: Science/Research
Classifier: Topic :: Software Development :: Libraries :: Python Modules
Classifier: Topic :: Scientific/Engineering :: Information Analysis
Classifier: Topic :: Internet :: WWW/HTTP :: Dynamic Content
Classifier: License :: OSI Approved :: MIT License
Classifier: Programming Language :: Python :: 3
Classifier: Programming Language :: Python :: 3.8
Classifier: Programming Language :: Python :: 3.9
Classifier: Programming Language :: Python :: 3.10
Classifier: Programming Language :: Python :: 3.11
Classifier: Programming Language :: Python :: 3.12
Classifier: Operating System :: OS Independent
Classifier: Environment :: Console
Classifier: Environment :: Web Environment
Requires-Python: >=3.8
License-File: LICENSE
Requires-Dist: requests>=2.31.0
Requires-Dist: python-dotenv>=1.0.0
Requires-Dist: schedule>=1.2.0
Requires-Dist: click>=8.1.0
Requires-Dist: pandas>=2.0.0
Requires-Dist: numpy>=1.24.0
Requires-Dist: pytz>=2023.3
Requires-Dist: jsonschema>=4.17.0
Requires-Dist: pydantic>=2.0.0
Requires-Dist: sqlalchemy>=2.0.0
Requires-Dist: psutil>=5.9.0
Requires-Dist: prometheus-client>=0.17.0
Provides-Extra: dev
Requires-Dist: pytest>=7.4.0; extra == "dev"
Requires-Dist: pytest-cov>=4.1.0; extra == "dev"
Requires-Dist: black>=23.0.0; extra == "dev"
Requires-Dist: flake8>=6.0.0; extra == "dev"
Requires-Dist: mypy>=1.4.0; extra == "dev"
Requires-Dist: pre-commit>=3.0.0; extra == "dev"
Provides-Extra: postgres
Requires-Dist: psycopg2-binary>=2.9.0; extra == "postgres"
Provides-Extra: mongodb
Requires-Dist: pymongo>=4.4.0; extra == "mongodb"
Provides-Extra: all
Requires-Dist: psycopg2-binary>=2.9.0; extra == "all"
Requires-Dist: pymongo>=4.4.0; extra == "all"
Dynamic: license-file
